pytest_netdut/__init__.py
pytest_netdut/factories.py
pytest_netdut/px.py
pytest_netdut/utils.py
pytest_netdut/wrappers.py
pytest_netdut-0.14.1.dist-info/METADATA
pytest_netdut-0.14.1.dist-info/WHEEL
pytest_netdut-0.14.1.dist-info/top_level.txt
pytest_netdut-0.14.1.dist-info/RECORD
