Metadata-Version: 2.4
Name: pytest_netdut
Version: 0.14.1
Summary: "Automated software testing for switches using pytest"
Home-page: https://github.com/aristanetworks/pytest-netdut
Author: "David Snowdon"
Author-email: "daves@arista.com"
Maintainer: "Alex Webster"
Maintainer-email: "alexw@arista.com"
License: "BSD 3-Clause License"
Project-URL: Source, https://github.com/aristanetworks/pytest-netdut/
Project-URL: Tracker, https://github.com/aristanetworks/pytest-netdut/issues
Project-URL: Documentation, https://github.com/aristanetworks/pytest-netdut/
Keywords: pytest,eos
Classifier: License :: OSI Approved :: BSD License
Classifier: Operating System :: OS Independent
Classifier: Programming Language :: Python :: 3
Classifier: Framework :: Pytest
Classifier: Intended Audience :: Developers
Classifier: Topic :: Software Development :: Testing
Requires-Dist: pexpect>=4.8.0
Requires-Dist: pyeapi>=0.8.4
Requires-Dist: pytest>=3.5.0
Requires-Dist: six>=1.15
Requires-Dist: packaging>=22.0
